sphinx_inplace/__init__.py
sphinx_inplace/__main__.py
sphinx_inplace/file_tree.py
sphinx_inplace/rst_generator.py
sphinx_inplace/template/module.rst_t
sphinx_inplace/template/package.rst_t
sphinx_inplace/template/toc.rst_t
sphinx_inplace-0.0.7.dist-info/LICENSE
sphinx_inplace-0.0.7.dist-info/METADATA
sphinx_inplace-0.0.7.dist-info/WHEEL
sphinx_inplace-0.0.7.dist-info/top_level.txt
sphinx_inplace-0.0.7.dist-info/RECORD
