Metadata-Version: 2.1
Name: sphinx-inplace
Version: 0.0.7
Summary: Automatically manage *.rst files in sphinx projects
Home-page: https://github.com/panhaoyu/sphinx-inplace
Author: Haoyu Pan
Author-email: panhaoyu.china@outlook.com
License: UNKNOWN
Project-URL: Bug Tracker, https://github.com/panhaoyu/sphinx-inplace/issues
Platform: UNKNOWN
Classifier: Programming Language :: Python :: 3
Classifier: License :: OSI Approved :: MIT License
Classifier: Operating System :: OS Independent
Requires-Python: >=3.8
License-File: LICENSE
Requires-Dist: sphinx
